{
  "properties": [
    {
      "name": "spring.chaser.datasource.driver-class-name",
      "type": "java.lang.String",
      "description": "Fully qualified name of the JDBC driver for vom chaser."
    },
    {
      "name": "spring.chaser.datasource.url",
      "type": "java.lang.String",
      "description": "Chaser db url."
    },
    {
      "name": "spring.chaser.datasource.username",
      "type": "java.lang.String",
      "description": "stay default."
    },
    {
      "name": "spring.chaser.datasource.password",
      "type": "java.lang.String",
      "description": "stay empty."
    }
  ]
}
